verilog_src/poly_arithmetic/mocking/q_const_mult.v
`timescale 1ns / 1ps


module q_const_mult
(
    input CLK,
    input [63:0] A,
    output [127:0] P
);

localparam q = 64'd18434813901432784897;
reg [127:0] P_delay [2:0];

always @(posedge CLK)
begin
    P_delay[0] <= A * q;
    P_delay[1] <= P_delay[0];
    P_delay[2] <= P_delay[1];
end

assign P = P_delay[2];

endmodule

verilog_src/poly_arithmetic/mocking/mu_const_mult.v
`timescale 1ns / 1ps


module mu_const_mult
(
    input CLK,
    input [63:0] A,
    output [127:0] P
);

localparam mu= 65'd18458681966650671896;
reg [127:0] P_delay [2:0];

always @(posedge CLK)
begin
    P_delay[0] <= A * (mu >> 1);
    P_delay[1] <= P_delay[0];
    P_delay[2] <= P_delay[1];
end

assign P = P_delay[2];

endmodule

verilog_src/poly_arithmetic/mocking/mult_64.v
`timescale 1ns / 1ps


module mult_64
(
    input CLK,
    input [63:0] A,
    input [63:0] B,
    output [127:0] P
);

wire [127:0] P_next = A * B;
reg [127:0] P_delay [5:0];

always @(posedge CLK) begin
    //$write("A %016x ", A);
    //$write("B %016x ", B);
    //$write("P_next %016x ", P_next);
    //$write("P %016x ", P);
    //$display("");
    P_delay[0] <= P_next;
    P_delay[1] <= P_delay[0];
    P_delay[2] <= P_delay[1];
    P_delay[3] <= P_delay[2];
    P_delay[4] <= P_delay[3];
    P_delay[5] <= P_delay[4];
end

assign P = P_delay[5];

endmodule

verilog_src/poly_arithmetic/polynomial_multiplication.v
`timescale 1ns / 1ps
//////////////////////////////////////////////////////////////////////////////////
// Company: 
// Engineer: 
// 
// Create Date: 01/14/2022 03:14:43 PM
// Design Name: 
// Module Name: polynomial_64_multiplication
// Project Name: 
// Target Devices: 
// Tool Versions: 
// Description: 
// 
// Dependencies: 
// 
// Revision:
// Revision 0.01 - File Created
// Additional Comments:
// 
//////////////////////////////////////////////////////////////////////////////////

module modular_multiplier(clk, mul_ina, mul_inb, mul_start, mul_out, mul_done);

localparam q       = 64'd18434813901432784897;
localparam qx      = 65'd18434813901432784897;
localparam mu      = 65'd18458681966650671896;
localparam DELAY   = 14;
localparam S_DELAY = 2; // 2 = 3 cycles delay
localparam MUL_DELAY = 3+3-1; // 5 = 6 cycles delay

input clk;
input [63:0] mul_ina, mul_inb;
input mul_start;
output [63:0] mul_out;
output mul_done;

reg [63:0] mul_ina_reg, mul_inb_reg;
reg [127:0] mul_delay [MUL_DELAY:0];
reg [64:0] s_delay [S_DELAY:0];

reg [DELAY:0] done_delay;

wire [127:0] int_mul_result;
wire [127:0] rx_low;
wire [127:0] sx_low, sx_high;

reg [63:0] result;

//    D = A * B
//
mult_64 MUL_64 (.CLK(clk), .A(mul_ina_reg), .B(mul_inb_reg), .P(int_mul_result));
mu_const_mult MU_MUL_LOW (.CLK(clk), .A(int_mul_result[63:0]), .P(sx_low));
mu_const_mult MU_MUL_HIGH (.CLK(clk), .A(int_mul_result[127:64]), .P(sx_high));
q_const_mult Q_MUL_LOW (.CLK(clk), .A(s[63:0]), .P(rx_low));

wire [192:0] sx = ((sx_high << 64) + sx_low) << 1;
wire [64:0] s = sx[192:128];
wire [64:0] r = ((s_delay[S_DELAY][64] * q) << 64) + rx_low;
wire [64:0] u = mul_delay[MUL_DELAY][64:0] - r;
wire [63:0] reduced_val = (u >= qx) ? (u - q) : u;

//    s = (D * mu) >> 128
//
//wire [192:0] sx_ref = int_mul_result * mu;
//wire [64:0] s_ref = sx_ref[192:128];

//    D_low = int_mul_result[63:0]
//    D_high = int_mul_result[127:64]

// Way #1: naive addition (needs to be synced with flip-flops).
// NOTE(abi): use 64-bit mu as the cte. for the IP multiplier (cut off MSB).
//wire [192:0] sx = ((mul_1 + sx_high) << 64) + sx_low;

// Way #2: bit shifting trick (no flip-flop needed for int_mul_result).
// NOTE(abi): use mu >> 1 as the cte. for the IP multiplier.

// NOTE(abi): we only need the upper 65 bits.

//    r = s * q
//
// NOTE(abi): we only need the lower 65 bits for the correction.
//wire [64:0] r_ref = s * q;



//    u = D - r
//

//    C = u - q if(u >= q) else u
//

generate 
    for (genvar i=1; i<=S_DELAY; i=i+1) begin
        always @(posedge clk)
        begin
            s_delay[i] <= s_delay[i-1];
        end
    end
    for (genvar i=1; i<=MUL_DELAY; i=i+1) begin
        always @(posedge clk)
        begin
            mul_delay[i] <= mul_delay[i-1];
        end
    end
endgenerate

always @(posedge clk)
begin
    result <= reduced_val[63:0];
    mul_ina_reg <= mul_ina;
    mul_inb_reg <= mul_inb;
    done_delay <= {done_delay[DELAY-1:0], mul_start};
    s_delay[0] <= s;
    mul_delay[0] <= int_mul_result;
end

assign mul_out = result;
assign mul_done = done_delay[DELAY];

endmodule

 

module polynomial_multiplication(clk, rst, mode, read_poly_op_sel, read_address, write_address, wea,
                                 data128_in, done, data128_out);

input clk;
input rst;                      // Active high
input [1:0] mode;               // 00 -> NTT, 01 -> inv-NTT, 10 -> element-wise mult
output [9:0] read_address;      // BRAM address for reading a 64-bit word
output read_poly_op_sel;        // Select one of the two polynomial operands
input [127:0] data128_in;       // Word read from the BRAM

output [9:0] write_address;     // BRAM address where the result word will be written
output wea;                     // BRAM write enable signal. The data in the write-bus will get written when this is 1.
output [127:0] data128_out;     // Word to be written to BRAM in the memory address specified by write_address
output done;                    // This signal becomes 1 when a given polynomial multiplication gets computed. 
                                // After that it should stay 1 until rst becomes 1.
                                // (we only set it to 1 for one cycle, otherwise the cryptocore would not work)

reg [11:0] mode_reg;
reg [11:0] state;  
wire [11:0] last_state = mode_reg[1] ? (256+8+2+2+13) : (1024+8+2+2+13);
wire [11:0] nextstate = (state == last_state) ? 11'd0 : state + 1;
wire odd_cycle = ~state[0];            

wire forward = ~mode[0];
wire element_wise = mode[1];
wire input_start = (state <= 0) || (state == last_state);
wire output_start = (state <= 2+2+13) || (state == last_state); // 1 + butterfly_unit delay
wire [63:0] operand_a_in, operand_b_in, operand_w_in;
wire [63:0] operand_a_out, operand_b_out;    
wire input_reset = rst | input_start;

assign done = (state == last_state) ? 1'b1 : 1'b0;
assign wea = (state >= 8+2+2+13) && (state != last_state) && ((~element_wise) || (odd_cycle)); // 8 + output_start delay

polynomial_multiplication_input input_gen(
    .clk(clk),
    .rst(input_reset),
    .state(state),
    .forward(forward),
    .element_wise(element_wise),
    .read_address(read_address),
    .read_poly_op_sel(read_poly_op_sel),
    .data128_in(data128_in),
    .operand_a(operand_a_in),
    .operand_b(operand_b_in),
    .operand_w(operand_w_in)
); 
                           
butterfly_unit butterfly(
    .clk(clk),
    .rst(rst),
    .forward(forward),
    .element_wise(element_wise),
    .operand_a_in(operand_a_in),
    .operand_b_in(operand_b_in),
    .operand_w_in(operand_w_in),
    .operand_a_out(operand_a_out),
    .operand_b_out(operand_b_out)
);

polynomial_multiplication_output output_gen(
    .clk(clk),
    .rst(rst),
    .start(output_start),
    .state(state),
    .forward(forward),
    .element_wise(element_wise),
    .write_address(write_address),
    .data128_out(data128_out),
    .done(done),
    .result_a(operand_a_out),
    .result_b(operand_b_out)
);

always @(posedge clk)
begin
    if(rst)
        mode_reg <= 2'd0;
    else
        mode_reg <= mode;    
end

always @(posedge clk)
begin
    if(rst)
        state <= 11'd0;
    else
        state <= nextstate;    
end
                                        
endmodule

verilog_src/poly_arithmetic/tb/tb_modular_multiplication.v
`timescale 1ns / 1ps

module tb_modular_multiplication();

    reg clk;
    reg mult_rst;

    reg [63:0] test_data_a [2:0];
    reg [63:0] test_data_b [2:0];
    reg [8:0] i;
    reg [8:0] n_rec;
            
            
    reg [63:0] mul_ina, mul_inb; 
    wire [63:0] mul_out;
    reg mul_start; 
    wire mul_done;
            
    modular_multiplier Mult(
        .clk(clk),
        .mul_ina(mul_ina),
        .mul_inb(mul_inb),
        .mul_start(mul_start),
        .mul_out(mul_out),
        .mul_done(mul_done)
    );

    initial begin
        clk = 0;
        mult_rst = 1;
        mul_start = 0;
        mul_ina = 64'd0;
        mul_inb = 64'd0;
        #3;
        repeat(2) #10;
        mul_start = 1; 
        mul_ina = 64'd0; // 4
        mul_inb = 64'd1;
        #10;
        mul_ina = 64'd2; // 4
        mul_inb = 64'd3;
        #10;
        mul_ina = 64'd4; // 6
        mul_inb = 64'd5;
        #10;
        mul_ina = 64'd6;
        mul_inb = 64'd7;
        #10;
        mul_ina = 64'd8;
        mul_inb = 64'd9;
        #10;
        mul_ina = 64'd10;
        mul_inb = 64'd11;
        #10;
        mul_ina = 64'd12;
        mul_inb = 64'd13;
        #10;
        mul_ina = 64'd2; // 4
        mul_inb = 64'd1;
        #10;
        mul_ina = 64'd2; // 4
        mul_inb = 64'd1;
        #10;
        mul_ina = 64'd2; // 4
        mul_inb = 64'd1;
        #10;
        mul_ina = 64'd2; // 4
        mul_inb = 64'd1;
        #10;
        mul_ina = 64'd2; // 4
        mul_inb = 64'd1;
        #10;
        mul_ina = 64'd2; // 4
        mul_inb = 64'd1;
        #10;
        mul_ina = 64'd2; // 4
        mul_inb = 64'd1;
        #10;
        mul_ina = 64'd2; // 4
        mul_inb = 64'd1;
        #10;
        mul_ina = 64'd2; // 4
        mul_inb = 64'd1;
        #10;
        mul_ina = 64'd18434813901432784897; // 0
        mul_inb = 64'd1;
        #10;
        mul_ina = 64'd18434813901432784898; // 1
        mul_inb = 64'd1;
        #10;
        mul_ina = 64'd13901706437927406777; // 2165091042952656860 = 1e0bf2d51992b7dc
        mul_inb = 64'd15700958295376441594;
        #10;
        mul_ina = 64'd1835666423505824111; // 14699318972420960652 = cbfe78b99f4fb18c
        mul_inb = 64'd4408257175847215637;
        #10;
        mul_ina = 64'd2; // 4
        mul_inb = 64'd2;
        #10;
        mul_ina = 64'd2; // 4
        mul_inb = 64'd2;
        #10;
        mul_ina = 64'd2; // 4
        mul_inb = 64'd2;
        #10;
        mul_ina = 64'd2; // 4
        mul_inb = 64'd2;
        #10;
        mul_ina = 64'd2; // 4
        mul_inb = 64'd2;
        #10;
        mul_ina = 64'd2; // 4
        mul_inb = 64'd2;
        #10;
        mul_ina = 64'd2; // 4
        mul_inb = 64'd2;
        #10;
        mul_ina = 64'd1835666423505824111; // 14699318972420960652 = cbfe78b99f4fb18c
        mul_inb = 64'd4408257175847215637;
        #10;
        mul_ina = 64'd2; // 4
        mul_inb = 64'd2;
        #10;
        mul_ina = 64'd2; // 4
        mul_inb = 64'd2;
        #10;
        mul_ina = 64'd2; // 4
        mul_inb = 64'd2;
        #10;
        mul_ina = 64'd2; // 4
        mul_inb = 64'd2;
        #10;
        mul_ina = 64'd2; // 4
        mul_inb = 64'd2;
        #10;
        mul_ina = 64'd2; // 4
        mul_inb = 64'd2;
        #10;
        mul_ina = 64'd2; // 4
        mul_inb = 64'd2;
        #10;
        mul_start = 0;

        repeat(20) #10;
        $display("--- end ---");
        $finish;
    end

    always @(negedge clk) begin
        $write("start %01d ", mul_start);
        $write("ina %016x ", mul_ina);
        $write("inb %016x ", mul_inb);
        $write("done %01d ", mul_done);
        $write("out %08x ", mul_out);
        //$display("");
        //$write("mul_ina_reg %016x ", Mult.mul_ina_reg);
        //$write("mul_inb_reg %016x ", Mult.mul_inb_reg);
        //$write("int_mul_result %016x ", Mult.int_mul_result);
        //$write("sx_low %016x ", Mult.sx_low);
        //$write("sx_high %016x ", Mult.sx_high);
        //$display("");
        //$write("rx_low %016x ", Mult.rx_low);
        //$write("mul_1 %016x ", Mult.mul_1);
        //$write("s %016x ", Mult.s);
        //$write("r %016x ", Mult.result);
        //$display("");
        $display("");
    end


    initial
    begin
        $dumpfile("test.vcd");
        $dumpvars(0,tb_modular_multiplication);
    end


    always #5 clk = ~clk;


endmodule

verilog_src/poly_arithmetic/test.vcd
$date
	Tue Dec 13 23:11:26 2022
$end
$version
	Icarus Verilog
$end
$timescale
	1ps
$end
$scope module tb_modular_multiplication $end
$var wire 64 ! mul_out [63:0] $end
$var wire 1 " mul_done $end
$var reg 1 # clk $end
$var reg 64 $ mul_ina [63:0] $end
$var reg 64 % mul_inb [63:0] $end
$var reg 1 & mul_start $end
$var reg 1 ' mult_rst $end
$scope module Mult $end
$var wire 1 # clk $end
$var wire 128 ( int_mul_result [127:0] $end
$var wire 64 ) mul_ina [63:0] $end
$var wire 64 * mul_inb [63:0] $end
$var wire 64 + mul_out [63:0] $end
$var wire 1 & mul_start $end
$var wire 128 , rx_low [127:0] $end
$var wire 128 - sx_high [127:0] $end
$var wire 128 . sx_low [127:0] $end
$var wire 65 / u [64:0] $end
$var wire 193 0 sx [192:0] $end
$var wire 65 1 s [64:0] $end
$var wire 64 2 reduced_val [63:0] $end
$var wire 65 3 r [64:0] $end
$var wire 1 " mul_done $end
$var reg 15 4 done_delay [14:0] $end
$var reg 64 5 mul_ina_reg [63:0] $end
$var reg 64 6 mul_inb_reg [63:0] $end
$var reg 64 7 result [63:0] $end
$scope begin genblk1[1] $end
$upscope $end
$scope begin genblk1[2] $end
$upscope $end
$scope begin genblk2[1] $end
$upscope $end
$scope begin genblk2[2] $end
$upscope $end
$scope begin genblk2[3] $end
$upscope $end
$scope begin genblk2[4] $end
$upscope $end
$scope begin genblk2[5] $end
$upscope $end
$scope module MUL_64 $end
$var wire 64 8 A [63:0] $end
$var wire 64 9 B [63:0] $end
$var wire 1 # CLK $end
$var wire 128 : P [127:0] $end
$var wire 128 ; P_next [127:0] $end
$upscope $end
$scope module MU_MUL_HIGH $end
$var wire 64 < A [63:0] $end
$var wire 1 # CLK $end
$var wire 128 = P [127:0] $end
$upscope $end
$scope module MU_MUL_LOW $end
$var wire 64 > A [63:0] $end
$var wire 1 # CLK $end
$var wire 128 ? P [127:0] $end
$upscope $end
$scope module Q_MUL_LOW $end
$var wire 64 @ A [63:0] $end
$var wire 1 # CLK $end
$var wire 128 A P [127:0] $end
$upscope $end
$upscope $end
$upscope $end
$enddefinitions $end
#0
$dumpvars
bx A
bx @
bx ?
bx >
bx =
bx <
bx ;
bx :
bx 9
bx 8
bx 7
bx 6
bx 5
bx 4
bx 3
bx 2
bx 1
bx0 0
bx /
bx .
bx -
bx ,
bx +
b0 *
b0 )
bx (
1'
0&
b0 %
b0 $
0#
x"
bx !
$end
#5000
bx0 4
b0 ;
b0 6
b0 9
b0 5
b0 8
1#
#10000
0#
#15000
bx00 4
1#
#20000
0#
#23000
b1 %
b1 *
1&
#25000
bx001 4
b1 6
b1 9
1#
#30000
0#
#33000
b11 %
b11 *
b10 $
b10 )
#35000
bx0011 4
b11 6
b11 9
b110 ;
b10 5
b10 8
1#
#40000
0#
#43000
b101 %
b101 *
b100 $
b100 )
#45000
bx00111 4
b101 6
b101 9
b10100 ;
b100 5
b100 8
1#
#50000
0#
#53000
b111 %
b111 *
b110 $
b110 )
#55000
bx001111 4
b111 6
b111 9
b101010 ;
b110 5
b110 8
1#
#60000
0#
#63000
b1001 %
b1001 *
b1000 $
b1000 )
#65000
b0 >
b0 <
b0 (
b0 :
bx0011111 4
b1001 6
b1001 9
b1001000 ;
b1000 5
b1000 8
1#
#70000
0#
#73000
b1011 %
b1011 *
b1010 $
b1010 )
#75000
bx00111111 4
b1011 6
b1011 9
b1101110 ;
b1010 5
b1010 8
1#
#80000
0#
#83000
b1101 %
b1101 *
b1100 $
b1100 )
#85000
bx001111111 4
b1101 6
b1101 9
b10011100 ;
b1100 5
b1100 8
1#
#90000
0#
#93000
b1 %
b1 *
b10 $
b10 )
#95000
b0 @
b0 1
b0 0
b110 >
bx0011111111 4
b1 6
b1 9
b10 ;
b10 5
b10 8
b0 -
b0 =
b0 .
b0 ?
b110 (
b110 :
1#
#100000
0#
#105000
b10100 >
b10100 (
b10100 :
bx00111111111 4
1#
#110000
0#
#115000
b101010 >
bx001111111111 4
b101010 (
b101010 :
1#
#120000
0#
#125000
b0 2
b0 /
b0 3
b1001000 >
b1100000000011111110011110001011001111001000101110111001001010010000 0
b1001000 (
b1001000 :
b110000000001111111001111000101100111100100010111011100100101001000 .
b110000000001111111001111000101100111100100010111011100100101001000 ?
b0 ,
b0 A
bx0011111111111 4
1#
#130000
0#
#135000
b101000000001101010000001111010000000111110010011100010011110111100000 0
b1101110 >
bx00111111111111 4
b0 !
b0 +
b0 7
b10100000000110101000000111101000000011111001001110001001111011110000 .
b10100000000110101000000111101000000011111001001110001001111011110000 ?
b1101110 (
b1101110 :
1#
#140000
0#
#145000
b10011100 >
b1010100000011011110101010011001110101001111101001000010000000111110000 0
0"
b10011100 (
b10011100 :
b101010000001101111010101001100111010100111110100100001000000011111000 .
b101010000001101111010101001100111010100111110100100001000000011111000 ?
b1111111111111 4
1#
#150000
0#
#155000
b110 2
b10010000000101111101101101010000110110101101000110010101101111011000000 0
b10 >
b110 /
b11111111111111 4
b1001000000010111110110110101000011011010110100011001010110111101100000 .
b1001000000010111110110110101000011011010110100011001010110111101100000 ?
b10 (
b10 :
1#
#160000
0#
#165000
b10100 2
b10100 /
b11011100001001000111001010011111000101010110101011011101101010001010000 0
1"
b1101110000100100011100101001111100010101011010101101110110101000101000 .
b1101110000100100011100101001111100010101011010101101110110101000101000 ?
b111111111111111 4
b110 !
b110 +
b110 7
1#
#170000
0#
#175000
b101010 2
b100111000001100111011000010000100100001001100011000011001110001010100000 0
b101010 /
b10100 !
b10100 +
b10100 7
b10011100000110011101100001000010010000100110001100001100111000101010000 .
b10011100000110011101100001000010010000100110001100001100111000101010000 ?
1#
#180000
0#
#183000
b1111111111010101100111011001001001001111010101011000100000000001 $
b1111111111010101100111011001001001001111010101011000100000000001 )
#185000
b1001000 2
b1001000 /
b100000000001010100110100101110011010011000001111101000011000110000 0
b10000000000101010011010010111001101001100000111110100001100011000 .
b10000000000101010011010010111001101001100000111110100001100011000 ?
b1111111111010101100111011001001001001111010101011000100000000001 ;
b1111111111010101100111011001001001001111010101011000100000000001 5
b1111111111010101100111011001001001001111010101011000100000000001 8
b101010 !
b101010 +
b101010 7
1#
#190000
0#
#193000
b1111111111010101100111011001001001001111010101011000100000000010 $
b1111111111010101100111011001001001001111010101011000100000000010 )
#195000
b1101110 2
b1101110 /
b1111111111010101100111011001001001001111010101011000100000000010 ;
b1111111111010101100111011001001001001111010101011000100000000010 5
b1111111111010101100111011001001001001111010101011000100000000010 8
b1001000 !
b1001000 +
b1001000 7
1#
#200000
0#
#203000
b1101100111100101000000100110000111100101001000101011000011111010 %
b1101100111100101000000100110000111100101001000101011000011111010 *
b1100000011101100110010000101100111010100011011001000110010111001 $
b1100000011101100110010000101100111010100011011001000110010111001 )
#205000
b10011100 2
b10011100 /
b1101100111100101000000100110000111100101001000101011000011111010 6
b1101100111100101000000100110000111100101001000101011000011111010 9
b10100100001101010100101101101110111111010110000110011010000111110011000010100100011111100010100101000000010100101001110010101010 ;
b1100000011101100110010000101100111010100011011001000110010111001 5
b1100000011101100110010000101100111010100011011001000110010111001 8
b1101110 !
b1101110 +
b1101110 7
1#
#210000
0#
#213000
b11110100101101010001101000101110100100111100001010001000010101 %
b11110100101101010001101000101110100100111100001010001000010101 *
b1100101111001100110001110001011101011001011010010100101101111 $
b1100101111001100110001110001011101011001011010010100101101111 )
#215000
b10 2
b10 /
b11110100101101010001101000101110100100111100001010001000010101 6
b11110100101101010001101000101110100100111100001010001000010101 9
b110000101100111101011010011000101110010101100000001011001011000001101111011011001011001011011010010111111001010010000011011 ;
b1100101111001100110001110001011101011001011010010100101101111 5
b1100101111001100110001110001011101011001011010010100101101111 8
b10011100 !
b10011100 +
b10011100 7
1#
#220000
0#
#223000
b10 %
b10 *
b10 $
b10 )
#225000
b10 6
b10 9
b100 ;
b10 5
b10 8
b10 !
b10 +
b10 7
1#
#230000
0#
#235000
1#
#240000
0#
#245000
b1111111111010101100111011001001001001111010101011000100000000001 >
b1111111111010101100111011001001001001111010101011000100000000001 (
b1111111111010101100111011001001001001111010101011000100000000001 :
1#
#250000
0#
#255000
b1111111111010101100111011001001001001111010101011000100000000010 >
b1111111111010101100111011001001001001111010101011000100000000010 (
b1111111111010101100111011001001001001111010101011000100000000010 :
1#
#260000
0#
#265000
b11000010100100011111100010100101000000010100101001110010101010 >
b1010010000110101010010110110111011111101011000011001101000011111 <
b10100100001101010100101101101110111111010110000110011010000111110011000010100100011111100010100101000000010100101001110010101010 (
b10100100001101010100101101101110111111010110000110011010000111110011000010100100011111100010100101000000010100101001110010101010 :
1#
#270000
0#
#275000
b11111111111111111111111111111111111111111111111111111111111111110111000011100111100100011010100110010110101111000000001100011000 0
b1000001101111011011001011001011011010010111111001010010000011011 >
b11000010110011110101101001100010111001010110000000101100101 <
b1111111111111111111111111111111111111111111111111111111111111111011100001110011110010001101010011001011010111100000000110001100 .
b1111111111111111111111111111111111111111111111111111111111111111011100001110011110010001101010011001011010111100000000110001100 ?
b110000101100111101011010011000101110010101100000001011001011000001101111011011001011001011011010010111111001010010000011011 (
b110000101100111101011010011000101110010101100000001011001011000001101111011011001011001011011010010111111001010010000011011 :
1#
#280000
0#
#285000
b1 @
b1 1
b100 >
b0 <
b100000000000000000000000000000000000000000000000000000000000000000111000100010001111110110001110011100010110110110100011000110000 0
b100 (
b100 :
b10000000000000000000000000000000000000000000000000000000000000000011100010001000111111011000111001110001011011011010001100011000 .
b10000000000000000000000000000000000000000000000000000000000000000011100010001000111111011000111001110001011011011010001100011000 ?
1#
#290000
0#
#293000
b11110100101101010001101000101110100100111100001010001000010101 %
b11110100101101010001101000101110100100111100001010001000010101 *
b1100101111001100110001110001011101011001011010010100101101111 $
b1100101111001100110001110001011101011001011010010100101101111 )
#295000
b1010010001010000011111111101000100101110010011000111010011001101 @
b1010010001010000011111111101000100101110010011000111010011001101 1
b101001000101000001111111110100010010111001001100011101001100110111000010001110000100011101100111011111010110111100011000001010001001110111001010000010101001010100010111010101010010110111110000 0
b11110100101101010001101000101110100100111100001010001000010101 6
b11110100101101010001101000101110100100111100001010001000010101 9
b110000101100111101011010011000101110010101100000001011001011000001101111011011001011001011011010010111111001010010000011011 ;
b1100101111001100110001110001011101011001011010010100101101111 5
b1100101111001100110001110001011101011001011010010100101101111 8
b1010010001010000011111111101000100101110010011000111010011001101100100011000101110111010001110000010101000111101100011111110100 -
b1010010001010000011111111101000100101110010011000111010011001101100100011000101110111010001110000010101000111101100011111110100 =
b11000010101100100011010010111101010011001100011000100001000000100111011100101000001010100101010001011101010101001011011111000 .
b11000010101100100011010010111101010011001100011000100001000000100111011100101000001010100101010001011101010101001011011111000 ?
1#
#300000
0#
#303000
b10 %
b10 *
b10 $
b10 )
#305000
b0 2
b11000010111011111010000010100110100000101011111101010001111 @
b11000010111011111010000010100110100000101011111101010001111 1
b1111111111010101100111011001001001001111010101011000100000000001 /
b1100001011101111101000001010011010000010101111110101000111111001000101110001001000011010110111001101000111000000001111000000000011001001001010101111100110011001001111001110111001110001000 0
b1000001110010001001011011111111001010001111011010111000101101000000001100100100101010111110011001100100111100111011100111000100 .
b1000001110010001001011011111111001010001111011010111000101101000000001100100100101010111110011001100100111100111011100111000100 ?
b11000010111011111010000010100110100000101011111101010001111010001010010011101100010110110001001010010100000100100000111100 -
b11000010111011111010000010100110100000101011111101010001111010001010010011101100010110110001001010010100000100100000111100 =
b10 6
b10 9
b100 ;
b10 5
b10 8
1#
#310000
0#
#315000
b0 @
b0 1
b1 2
b1111111111010101100111011001001001001111010101011000100000000001 3
b1000000000010101001101001011100110100110000011111010000110001100000 0
b1 /
b0 !
b0 +
b0 7
b1111111111010101100111011001001001001111010101011000100000000001 ,
b1111111111010101100111011001001001001111010101011000100000000001 A
b0 -
b0 =
b100000000001010100110100101110011010011000001111101000011000110000 .
b100000000001010100110100101110011010011000001111101000011000110000 ?
1#
#320000
0#
#325000
b1111000001011111100101101010100011001100100101011011111011100 2
b10001110111100001100100000110011101101000111010000011111111011101 /
b1001011000010111011011100000111010111011010100101110011001101 3
b10100100001101010100101101101110111111010110000110011010000111100001001011000010111011011100000111010111011010100101110011001101 ,
b10100100001101010100101101101110111111010110000110011010000111100001001011000010111011011100000111010111011010100101110011001101 A
b1 !
b1 +
b1 7
1#
#330000
0#
#335000
b1100101111111110011110001011100110011111010011111011000110001100 2
b1011011101111100111011001101110100110011101011001111001010001111 3
b1100101111111110011110001011100110011111010011111011000110001100 /
b1111000001011111100101101010100011001100100101011011111011100 !
b1111000001011111100101101010100011001100100101011011111011100 +
b1111000001011111100101101010100011001100100101011011111011100 7
b110000101100111101011010011000101110010101100000001011001001011011101111100111011001101110100110011101011001111001010001111 ,
b110000101100111101011010011000101110010101100000001011001001011011101111100111011001101110100110011101011001111001010001111 A
1#
#340000
0#
#345000
b100 2
b100 /
b0 3
b0 ,
b0 A
b1100101111111110011110001011100110011111010011111011000110001100 !
b1100101111111110011110001011100110011111010011111011000110001100 +
b1100101111111110011110001011100110011111010011111011000110001100 7
1#
#350000
0#
#355000
b1000001101111011011001011001011011010010111111001010010000011011 >
b11000010110011110101101001100010111001010110000000101100101 <
b100 !
b100 +
b100 7
b110000101100111101011010011000101110010101100000001011001011000001101111011011001011001011011010010111111001010010000011011 (
b110000101100111101011010011000101110010101100000001011001011000001101111011011001011001011011010010111111001010010000011011 :
1#
#360000
0#
#365000
b100 >
b0 <
b100 (
b100 :
1#
#370000
0#
#373000
0&
#375000
b111111111111110 4
1#
#380000
0#
#385000
b11000010111011111010000010100110100000101011111101010001111 @
b11000010111011111010000010100110100000101011111101010001111 1
b1100001011101111101000001010011010000010101111110101000111111001000101110001001000011010110111001101000111000000001111000000000011001001001010101111100110011001001111001110111001110001000 0
b1000001110010001001011011111111001010001111011010111000101101000000001100100100101010111110011001100100111100111011100111000100 .
b1000001110010001001011011111111001010001111011010111000101101000000001100100100101010111110011001100100111100111011100111000100 ?
b11000010111011111010000010100110100000101011111101010001111010001010010011101100010110110001001010010100000100100000111100 -
b11000010111011111010000010100110100000101011111101010001111010001010010011101100010110110001001010010100000100100000111100 =
b111111111111100 4
1#
#390000
0#
#395000
b0 @
b0 1
b1000000000010101001101001011100110100110000011111010000110001100000 0
b111111111111000 4
b0 -
b0 =
b100000000001010100110100101110011010011000001111101000011000110000 .
b100000000001010100110100101110011010011000001111101000011000110000 ?
1#
#400000
0#
#405000
b111111111110000 4
1#
#410000
0#
#415000
b1100101111111110011110001011100110011111010011111011000110001100 2
b1011011101111100111011001101110100110011101011001111001010001111 3
b1100101111111110011110001011100110011111010011111011000110001100 /
b111111111100000 4
b110000101100111101011010011000101110010101100000001011001001011011101111100111011001101110100110011101011001111001010001111 ,
b110000101100111101011010011000101110010101100000001011001001011011101111100111011001101110100110011101011001111001010001111 A
1#
#420000
0#
#425000
b100 2
b100 /
b0 3
b0 ,
b0 A
b111111111000000 4
b1100101111111110011110001011100110011111010011111011000110001100 !
b1100101111111110011110001011100110011111010011111011000110001100 +
b1100101111111110011110001011100110011111010011111011000110001100 7
1#
#430000
0#
#435000
b111111110000000 4
b100 !
b100 +
b100 7
1#
#440000
0#
#445000
b111111100000000 4
1#
#450000
0#
#455000
b111111000000000 4
1#
#460000
0#
#465000
b111110000000000 4
1#
#470000
0#
#475000
b111100000000000 4
1#
#480000
0#
#485000
b111000000000000 4
1#
#490000
0#
#495000
b110000000000000 4
1#
#500000
0#
#505000
b100000000000000 4
1#
#510000
0#
#515000
0"
b0 4
1#
